<bbgame source="Basketball LiveStats In-Arena Tool" toolVersion="1.25.0" version="1.1.1" generated="Mar 3, 2021">
  <venue gameid="121841" visid="ZAC" visname="Zachodniopomorskie" homeid="ZAC" homename="Zachodniopomorskie" date="03/03/2021" location="Hala Sportowa ZSB" start="09:00 AM" leaguegame="N" neutralgame="N" nitegame="N" postseason="N">
    <officials text="Ignacy Suwała, Sylwester Adamski, Sebastian Kotowski">
    </officials>
    <rules prds="4" minutes="10" minutesot="5" fouls="5" qh="Q">
    </rules>
  </venue>
  <status complete="N" period="1" clock="06:15" running="F">
  </status>
  <team vh="V" code="793" id="ZAC" name="Zachodniopomorskie">
    <linescore line="5" score="5">
      <lineprd prd="1" score="5">
      </lineprd>
    </linescore>
    <totals>
      <stats fgm="2" fga="5" fgm3="0" fga3="2" ftm="1" fta="2" tp="5" blk="1" stl="2" ast="1" min="19" oreb="1" dreb="3" treb="4" pf="2" tf="0" to="4" dq="0" fgpct="40" fg3pct="0" ftpct="50">
      </stats>
      <special vh="V" pts_to="2" pts_ch2="0" pts_paint="4" pts_fastb="0" pts_bench="0" ties="0" leads="0" lead_time="100" large_lead="2">
      </special>
      <statsbyprd prd="1" fgm="2" fga="5" fgm3="0" fga3="2" ftm="1" fta="2" tp="5" blk="1" stl="2" ast="1" min="19" oreb="1" dreb="3" treb="4" pf="2" tf="0" to="4" dq="0">
      </statsbyprd>
    </totals>
    <player uni="5" code="5" name="Wojdak, Jakub" checkname="WOJDAK,JAKUB" class="" gp="0" gs="0" pos="P" oncourt="N">
      <stats fgm="0" fga="0" fgm3="0" fga3="0" ftm="0" fta="0" tp="0" blk="0" stl="0" ast="0" min="0" oreb="0" dreb="0" treb="0" pf="0" tf="0" to="0" dq="0" fgpct="0" fg3pct="0" ftpct="0">
      </stats>
    </player>
    <player uni="7" code="7" name="Berliński, Vincent" checkname="BERLIŃSKI,VINCENT" class="" gp="1" gs="1" pos="S" oncourt="Y">
      <stats fgm="1" fga="1" fgm3="0" fga3="0" ftm="0" fta="0" tp="2" blk="0" stl="1" ast="1" min="4" sec="-" oreb="0" dreb="0" treb="0" pf="0" tf="0" to="1" dq="0" fgpct="100" fg3pct="0" ftpct="0">
      </stats>
      <statsbyprd prd="1" fgm="1" fga="1" fgm3="0" fga3="0" ftm="0" fta="0" tp="2" blk="0" stl="1" ast="1" min="4" sec="-" oreb="0" dreb="0" treb="0" pf="0" tf="0" to="1" dq="0">
      </statsbyprd>
    </player>
    <player uni="8" code="8" name="Dębicki, Maciej" checkname="DĘBICKI,MACIEJ" class="" gp="1" gs="0" pos="P" oncourt="N">
      <stats fgm="0" fga="0" fgm3="0" fga3="0" ftm="0" fta="0" tp="0" blk="0" stl="0" ast="0" min="1" oreb="0" dreb="0" treb="0" pf="0" tf="0" to="0" dq="0" fgpct="0" fg3pct="0" ftpct="0">
      </stats>
      <statsbyprd prd="1" fgm="0" fga="0" fgm3="0" fga3="0" ftm="0" fta="0" tp="0" blk="0" stl="0" ast="0" min="1" sec="+" oreb="0" dreb="0" treb="0" pf="0" tf="0" to="0" dq="0">
      </statsbyprd>
    </player>
    <player uni="9" code="9" name="Dąbrowski, Mateusz" checkname="DĄBROWSKI,MATEUSZ" class="" gp="0" gs="0" pos="S" oncourt="N">
      <stats fgm="0" fga="0" fgm3="0" fga3="0" ftm="0" fta="0" tp="0" blk="0" stl="0" ast="0" min="0" oreb="0" dreb="0" treb="0" pf="0" tf="0" to="0" dq="0" fgpct="0" fg3pct="0" ftpct="0">
      </stats>
    </player>
    <player uni="10" code="10" name="Kaspruk, Sebastian" checkname="KASPRUK,SEBASTIAN" class="" gp="0" gs="0" pos="S" oncourt="N">
      <stats fgm="0" fga="0" fgm3="0" fga3="0" ftm="0" fta="0" tp="0" blk="0" stl="0" ast="0" min="0" oreb="0" dreb="0" treb="0" pf="0" tf="0" to="0" dq="0" fgpct="0" fg3pct="0" ftpct="0">
      </stats>
    </player>
    <player uni="11" code="11" name="Chac, Franciszek" checkname="CHAC,FRANCISZEK" class="" gp="1" gs="1" pos="P" oncourt="Y">
      <stats fgm="1" fga="3" fgm3="0" fga3="2" ftm="0" fta="0" tp="2" blk="0" stl="0" ast="0" min="4" sec="-" oreb="0" dreb="1" treb="1" pf="0" tf="0" to="1" dq="0" fgpct="33.3" fg3pct="0" ftpct="0">
      </stats>
      <statsbyprd prd="1" fgm="1" fga="3" fgm3="0" fga3="2" ftm="0" fta="0" tp="2" blk="0" stl="0" ast="0" min="4" sec="-" oreb="0" dreb="1" treb="1" pf="0" tf="0" to="1" dq="0">
      </statsbyprd>
    </player>
    <player uni="12" code="12" name="Pankiewicz, Wiktor" checkname="PANKIEWICZ,WIKTOR" class="" gp="0" gs="0" pos="S" oncourt="N">
      <stats fgm="0" fga="0" fgm3="0" fga3="0" ftm="0" fta="0" tp="0" blk="0" stl="0" ast="0" min="0" oreb="0" dreb="0" treb="0" pf="0" tf="0" to="0" dq="0" fgpct="0" fg3pct="0" ftpct="0">
      </stats>
    </player>
    <player uni="13" code="13" name="Ulaszewski, Jan" checkname="ULASZEWSKI,JAN" class="" gp="0" gs="0" pos="C" oncourt="N">
      <stats fgm="0" fga="0" fgm3="0" fga3="0" ftm="0" fta="0" tp="0" blk="0" stl="0" ast="0" min="0" oreb="0" dreb="0" treb="0" pf="0" tf="0" to="0" dq="0" fgpct="0" fg3pct="0" ftpct="0">
      </stats>
    </player>
    <player uni="14" code="14" name="Siergiej, Cezary" checkname="SIERGIEJ,CEZARY" class="" gp="1" gs="1" pos="P" oncourt="Y">
      <stats fgm="0" fga="0" fgm3="0" fga3="0" ftm="0" fta="0" tp="0" blk="0" stl="0" ast="0" min="4" sec="-" oreb="0" dreb="0" treb="0" pf="1" tf="0" to="0" dq="0" fgpct="0" fg3pct="0" ftpct="0">
      </stats>
      <statsbyprd prd="1" fgm="0" fga="0" fgm3="0" fga3="0" ftm="0" fta="0" tp="0" blk="0" stl="0" ast="0" min="4" sec="-" oreb="0" dreb="0" treb="0" pf="1" tf="0" to="0" dq="0">
      </statsbyprd>
    </player>
    <player uni="15" code="15" name="Jarosz, Maciej" checkname="JAROSZ,MACIEJ" class="" gp="1" gs="1" pos="S" oncourt="Y">
      <stats fgm="0" fga="1" fgm3="0" fga3="0" ftm="1" fta="2" tp="1" blk="0" stl="1" ast="0" min="4" sec="-" oreb="0" dreb="0" treb="0" pf="1" tf="0" to="0" dq="0" fgpct="0" fg3pct="0" ftpct="50">
      </stats>
      <statsbyprd prd="1" fgm="0" fga="1" fgm3="0" fga3="0" ftm="1" fta="2" tp="1" blk="0" stl="1" ast="0" min="4" sec="-" oreb="0" dreb="0" treb="0" pf="1" tf="0" to="0" dq="0">
      </statsbyprd>
    </player>
    <player uni="16" code="16" name="Woźniak, Filip" checkname="WOŹNIAK,FILIP" class="" gp="1" gs="1" pos="F" oncourt="Y">
      <stats fgm="0" fga="0" fgm3="0" fga3="0" ftm="0" fta="0" tp="0" blk="1" stl="0" ast="0" min="2" sec="+" oreb="1" dreb="2" treb="3" pf="0" tf="0" to="2" dq="0" fgpct="0" fg3pct="0" ftpct="0">
      </stats>
      <statsbyprd prd="1" fgm="0" fga="0" fgm3="0" fga3="0" ftm="0" fta="0" tp="0" blk="1" stl="0" ast="0" min="2" sec="+" oreb="1" dreb="2" treb="3" pf="0" tf="0" to="2" dq="0">
      </statsbyprd>
    </player>
    <player uni="17" code="17" name="Kotrys, Maksymilian" checkname="KOTRYS,MAKSYMILIAN" class="" gp="0" gs="0" pos="C" oncourt="N">
      <stats fgm="0" fga="0" fgm3="0" fga3="0" ftm="0" fta="0" tp="0" blk="0" stl="0" ast="0" min="0" oreb="0" dreb="0" treb="0" pf="0" tf="0" to="0" dq="0" fgpct="0" fg3pct="0" ftpct="0">
      </stats>
    </player>
    <player uni="TM" code="TM" name="TEAM" checkname="TEAM" class="" gp="1" gs="0" oncourt="N">
      <stats oreb="0" dreb="0" treb="0" pf="0" tf="0" to="0" dq="0">
      </stats>
      <statsbyprd prd="1" fgm="0" fga="0" oreb="0" dreb="0" treb="0" pf="0" tf="0" to="0" dq="0">
      </statsbyprd>
    </player>
  </team>
  <team vh="H" code="807" id="ŚLĄ" name="Śląskie">
    <linescore line="3" score="3">
      <lineprd prd="1" score="3">
      </lineprd>
    </linescore>
    <totals>
      <stats fgm="1" fga="6" fgm3="0" fga3="1" ftm="1" fta="2" tp="3" blk="1" stl="2" ast="0" min="19" oreb="2" dreb="3" treb="5" pf="3" tf="0" to="4" dq="0" fgpct="16.7" fg3pct="0" ftpct="50">
      </stats>
      <special vh="H" pts_to="2" pts_ch2="0" pts_paint="2" pts_fastb="3" pts_bench="0" ties="0" leads="0" lead_time="0" large_lead="0">
      </special>
      <statsbyprd prd="1" fgm="1" fga="6" fgm3="0" fga3="1" ftm="1" fta="2" tp="3" blk="1" stl="2" ast="0" min="19" oreb="2" dreb="3" treb="5" pf="3" tf="0" to="4" dq="0">
      </statsbyprd>
    </totals>
    <player uni="4" code="4" name="Maciejewski, Paweł" checkname="MACIEJEWSKI,PAWEŁ" class="" gp="1" gs="1" pos="P" oncourt="N">
      <stats fgm="0" fga="2" fgm3="0" fga3="1" ftm="0" fta="0" tp="0" blk="0" stl="0" ast="0" min="3" oreb="0" dreb="0" treb="0" pf="0" tf="0" to="0" dq="0" fgpct="0" fg3pct="0" ftpct="0">
      </stats>
      <statsbyprd prd="1" fgm="0" fga="2" fgm3="0" fga3="1" ftm="0" fta="0" tp="0" blk="0" stl="0" ast="0" min="3" sec="+" oreb="0" dreb="0" treb="0" pf="0" tf="0" to="0" dq="0">
      </statsbyprd>
    </player>
    <player uni="5" code="5" name="Holisz, Nikodem " checkname="HOLISZ,NIKODEM " class="" gp="0" gs="0" pos="G" oncourt="N">
      <stats fgm="0" fga="0" fgm3="0" fga3="0" ftm="0" fta="0" tp="0" blk="0" stl="0" ast="0" min="0" oreb="0" dreb="0" treb="0" pf="0" tf="0" to="0" dq="0" fgpct="0" fg3pct="0" ftpct="0">
      </stats>
    </player>
    <player uni="6" code="6" name="Wiśniewski, Artur" checkname="WIŚNIEWSKI,ARTUR" class="" gp="0" gs="0" pos="G" oncourt="N">
      <stats fgm="0" fga="0" fgm3="0" fga3="0" ftm="0" fta="0" tp="0" blk="0" stl="0" ast="0" min="0" oreb="0" dreb="0" treb="0" pf="0" tf="0" to="0" dq="0" fgpct="0" fg3pct="0" ftpct="0">
      </stats>
    </player>
    <player uni="7" code="7" name="Chlebiej , Filip" checkname="CHLEBIEJ ,FILIP" class="" gp="1" gs="1" pos="G" oncourt="Y">
      <stats fgm="0" fga="0" fgm3="0" fga3="0" ftm="0" fta="0" tp="0" blk="1" stl="1" ast="0" min="4" sec="-" oreb="0" dreb="1" treb="1" pf="1" tf="0" to="0" dq="0" fgpct="0" fg3pct="0" ftpct="0">
      </stats>
      <statsbyprd prd="1" fgm="0" fga="0" fgm3="0" fga3="0" ftm="0" fta="0" tp="0" blk="1" stl="1" ast="0" min="4" sec="-" oreb="0" dreb="1" treb="1" pf="1" tf="0" to="0" dq="0">
      </statsbyprd>
    </player>
    <player uni="8" code="8" name="Kozieł , Jakub" checkname="KOZIEŁ ,JAKUB" class="" gp="1" gs="1" pos="G" oncourt="Y">
      <stats fgm="0" fga="1" fgm3="0" fga3="0" ftm="0" fta="0" tp="0" blk="0" stl="0" ast="0" min="4" sec="-" oreb="0" dreb="0" treb="0" pf="0" tf="0" to="2" dq="0" fgpct="0" fg3pct="0" ftpct="0">
      </stats>
      <statsbyprd prd="1" fgm="0" fga="1" fgm3="0" fga3="0" ftm="0" fta="0" tp="0" blk="0" stl="0" ast="0" min="4" sec="-" oreb="0" dreb="0" treb="0" pf="0" tf="0" to="2" dq="0">
      </statsbyprd>
    </player>
    <player uni="9" code="9" name="Wojdała  , Jakub" checkname="WOJDAŁA  ,JAKUB" class="" gp="0" gs="0" pos="G" oncourt="N">
      <stats fgm="0" fga="0" fgm3="0" fga3="0" ftm="0" fta="0" tp="0" blk="0" stl="0" ast="0" min="0" oreb="0" dreb="0" treb="0" pf="0" tf="0" to="0" dq="0" fgpct="0" fg3pct="0" ftpct="0">
      </stats>
    </player>
    <player uni="10" code="10" name="Pratsz, Jan" checkname="PRATSZ,JAN" class="" gp="1" gs="0" pos="G" oncourt="Y">
      <stats fgm="0" fga="0" fgm3="0" fga3="0" ftm="0" fta="0" tp="0" blk="0" stl="0" ast="0" min="0" sec="+" oreb="0" dreb="0" treb="0" pf="1" tf="0" to="1" dq="0" fgpct="0" fg3pct="0" ftpct="0">
      </stats>
      <statsbyprd prd="1" fgm="0" fga="0" fgm3="0" fga3="0" ftm="0" fta="0" tp="0" blk="0" stl="0" ast="0" min="0" sec="+" oreb="0" dreb="0" treb="0" pf="1" tf="0" to="1" dq="0">
      </statsbyprd>
    </player>
    <player uni="11" code="11" name="Kaczorek , Milan" checkname="KACZOREK ,MILAN" class="" gp="0" gs="0" pos="G" oncourt="N">
      <stats fgm="0" fga="0" fgm3="0" fga3="0" ftm="0" fta="0" tp="0" blk="0" stl="0" ast="0" min="0" oreb="0" dreb="0" treb="0" pf="0" tf="0" to="0" dq="0" fgpct="0" fg3pct="0" ftpct="0">
      </stats>
    </player>
    <player uni="12" code="12" name="Majewski , Miłosz" checkname="MAJEWSKI ,MIŁOSZ" class="" gp="0" gs="0" pos="F" oncourt="N">
      <stats fgm="0" fga="0" fgm3="0" fga3="0" ftm="0" fta="0" tp="0" blk="0" stl="0" ast="0" min="0" oreb="0" dreb="0" treb="0" pf="0" tf="0" to="0" dq="0" fgpct="0" fg3pct="0" ftpct="0">
      </stats>
    </player>
    <player uni="13" code="13" name="Skrok-Wolski, Maciej" checkname="SKROK-WOLSKI,MACIEJ" class="" gp="1" gs="1" pos="F" oncourt="Y">
      <stats fgm="0" fga="1" fgm3="0" fga3="0" ftm="1" fta="2" tp="1" blk="0" stl="0" ast="0" min="4" sec="-" oreb="1" dreb="1" treb="2" pf="1" tf="0" to="1" dq="0" fgpct="0" fg3pct="0" ftpct="50">
      </stats>
      <statsbyprd prd="1" fgm="0" fga="1" fgm3="0" fga3="0" ftm="1" fta="2" tp="1" blk="0" stl="0" ast="0" min="4" sec="-" oreb="1" dreb="1" treb="2" pf="1" tf="0" to="1" dq="0">
      </statsbyprd>
    </player>
    <player uni="14" code="14" name="Nowak , Seweryn " checkname="NOWAK ,SEWERYN " class="" gp="1" gs="1" pos="F" oncourt="Y">
      <stats fgm="1" fga="2" fgm3="0" fga3="0" ftm="0" fta="0" tp="2" blk="0" stl="1" ast="0" min="4" sec="-" oreb="0" dreb="0" treb="0" pf="0" tf="0" to="0" dq="0" fgpct="50" fg3pct="0" ftpct="0">
      </stats>
      <statsbyprd prd="1" fgm="1" fga="2" fgm3="0" fga3="0" ftm="0" fta="0" tp="2" blk="0" stl="1" ast="0" min="4" sec="-" oreb="0" dreb="0" treb="0" pf="0" tf="0" to="0" dq="0">
      </statsbyprd>
    </player>
    <player uni="16" code="16" name="Misztal, Kajetan" checkname="MISZTAL,KAJETAN" class="" gp="0" gs="0" pos="F" oncourt="N">
      <stats fgm="0" fga="0" fgm3="0" fga3="0" ftm="0" fta="0" tp="0" blk="0" stl="0" ast="0" min="0" oreb="0" dreb="0" treb="0" pf="0" tf="0" to="0" dq="0" fgpct="0" fg3pct="0" ftpct="0">
      </stats>
    </player>
    <player uni="TM" code="TM" name="TEAM" checkname="TEAM" class="" gp="1" gs="0" oncourt="N">
      <stats oreb="1" dreb="1" treb="2" pf="0" tf="0" to="0" dq="0">
      </stats>
      <statsbyprd prd="1" fgm="0" fga="0" oreb="1" dreb="1" treb="2" pf="0" tf="0" to="0" dq="0">
      </statsbyprd>
    </player>
  </team>
  <plays format="tokens">
    <period number="1" time="10:00">
      <special vh="V" pts_to="2" pts_ch2="0" pts_paint="4" pts_fastb="0" pts_bench="0" ties="0" leads="0" lead_time="0" large_lead="0">
      </special>
      <special vh="H" pts_to="2" pts_ch2="0" pts_paint="2" pts_fastb="3" pts_bench="0" ties="0" leads="0" lead_time="0" large_lead="0">
      </special>
      <summary vh="V" fgm="2" fga="5" fgm3="0" fga3="2" ftm="1" fta="2" blk="1" stl="2" ast="1" oreb="1" dreb="3" treb="4" pf="2" tf="0" to="4">
      </summary>
      <summary vh="H" fgm="1" fga="6" fgm3="0" fga3="1" ftm="1" fta="2" blk="1" stl="2" ast="0" oreb="1" dreb="2" treb="5" pf="3" tf="0" to="4">
      </summary>
      <play vh="H" time="09:48" uni="4" team="ŚLĄ" checkname="MACIEJEWSKI,PAWEŁ" action="MISS" type="3PTR" x="31.979999542236328" y="53.950000762939453" side="left">
      </play>
      <play vh="V" time="09:44" uni="16" team="ZAC" checkname="WOŹNIAK,FILIP" action="REBOUND" type="DEF" side="right">
      </play>
      <play vh="V" time="09:24" uni="7" team="ZAC" checkname="BERLIŃSKI,VINCENT" action="GOOD" type="JUMPER" paint="Y" vscore="2" hscore="0" x="92.199996948242188" y="59.889999389648438" side="right">
      </play>
      <play vh="V" time="09:09" uni="15" team="ZAC" checkname="JAROSZ,MACIEJ" action="FOUL" side="right">
      </play>
      <play vh="H" time="09:01" uni="8" team="ŚLĄ" checkname="KOZIEŁ ,JAKUB" action="MISS" type="JUMPER" paint="Y" x="10.449999809265137" y="52.2599983215332" side="left">
      </play>
      <play vh="H" time="08:59" uni="13" team="ŚLĄ" checkname="SKROK-WOLSKI,MACIEJ" action="REBOUND" type="OFF" side="left">
      </play>
      <play vh="H" time="08:59" uni="13" team="ŚLĄ" checkname="SKROK-WOLSKI,MACIEJ" action="MISS" type="JUMPER" paint="Y" x="12.319999694824219" y="62.9900016784668" side="left">
      </play>
      <play vh="V" time="08:59" uni="16" team="ZAC" checkname="WOŹNIAK,FILIP" action="BLOCK" side="right">
      </play>
      <play vh="H" time="08:59" uni="TM" team="ŚLĄ" checkname="TEAM" action="REBOUND" type="OFF" side="left">
      </play>
      <play vh="H" time="08:59" uni="13" team="ŚLĄ" checkname="SKROK-WOLSKI,MACIEJ" action="TURNOVER" side="left">
      </play>
      <play vh="V" time="08:59" uni="15" team="ZAC" checkname="JAROSZ,MACIEJ" action="STEAL" side="right">
      </play>
      <play vh="V" time="08:59" uni="11" team="ZAC" checkname="CHAC,FRANCISZEK" action="TURNOVER" side="right">
      </play>
      <play vh="H" time="08:59" uni="14" team="ŚLĄ" checkname="NOWAK ,SEWERYN " action="STEAL" side="left">
      </play>
      <play vh="H" time="08:56" uni="14" team="ŚLĄ" checkname="NOWAK ,SEWERYN " action="GOOD" type="LAYUP" fastb="Y" vscore="2" hscore="2" x="4.8400001525878906" y="57.340000152587891" side="left">
      </play>
      <play vh="V" time="08:49" uni="16" team="ZAC" checkname="WOŹNIAK,FILIP" action="TURNOVER" side="right">
      </play>
      <play vh="H" time="08:49" uni="7" team="ŚLĄ" checkname="CHLEBIEJ ,FILIP" action="STEAL" side="left">
      </play>
      <play vh="H" time="08:41" uni="4" team="ŚLĄ" checkname="MACIEJEWSKI,PAWEŁ" action="MISS" type="JUMPER" x="10.760000228881836" y="72.319999694824219" side="left">
      </play>
      <play vh="V" time="08:38" uni="16" team="ZAC" checkname="WOŹNIAK,FILIP" action="REBOUND" type="DEF" side="right">
      </play>
      <play vh="V" time="08:15" uni="11" team="ZAC" checkname="CHAC,FRANCISZEK" action="MISS" type="3PTR" x="71.139999389648438" y="27.680000305175781" side="right">
      </play>
      <play vh="H" time="08:12" uni="7" team="ŚLĄ" checkname="CHLEBIEJ ,FILIP" action="REBOUND" type="DEF" side="left">
      </play>
      <play vh="H" time="08:10" uni="8" team="ŚLĄ" checkname="KOZIEŁ ,JAKUB" action="TURNOVER" side="left">
      </play>
      <play vh="V" time="08:10" uni="16" team="ZAC" checkname="WOŹNIAK,FILIP" action="SUB" type="OUT" side="right">
      </play>
      <play vh="V" time="08:10" uni="8" team="ZAC" checkname="DĘBICKI,MACIEJ" action="SUB" type="IN" side="right">
      </play>
      <play vh="V" time="07:58" uni="7" team="ZAC" checkname="BERLIŃSKI,VINCENT" action="TURNOVER" side="right">
      </play>
      <play vh="H" time="07:39" uni="8" team="ŚLĄ" checkname="KOZIEŁ ,JAKUB" action="TURNOVER" side="left">
      </play>
      <play vh="V" time="07:27" uni="11" team="ZAC" checkname="CHAC,FRANCISZEK" action="GOOD" type="LAYUP" paint="Y" vscore="4" hscore="2" x="89.860000610351563" y="55.369998931884766" side="right">
      </play>
      <play vh="V" time="07:20" uni="14" team="ZAC" checkname="SIERGIEJ,CEZARY" action="FOUL" side="right">
      </play>
      <play vh="H" time="07:20" uni="13" team="ŚLĄ" checkname="SKROK-WOLSKI,MACIEJ" action="MISS" type="FT" fastb="Y" side="left">
      </play>
      <play vh="H" time="07:20" uni="TM" team="ŚLĄ" checkname="TEAM" action="REBOUND" type="DEADB" side="left">
      </play>
      <play vh="H" time="07:20" uni="13" team="ŚLĄ" checkname="SKROK-WOLSKI,MACIEJ" action="GOOD" type="FT" fastb="Y" vscore="4" hscore="3" side="left">
      </play>
      <play vh="H" time="07:10" uni="13" team="ŚLĄ" checkname="SKROK-WOLSKI,MACIEJ" action="FOUL" side="left">
      </play>
      <play vh="V" time="06:59" uni="11" team="ZAC" checkname="CHAC,FRANCISZEK" action="MISS" type="3PTR" x="67.860000610351563" y="51.979999542236328" side="right">
      </play>
      <play vh="H" time="06:56" uni="13" team="ŚLĄ" checkname="SKROK-WOLSKI,MACIEJ" action="REBOUND" type="DEF" side="left">
      </play>
      <play vh="H" time="06:52" uni="14" team="ŚLĄ" checkname="NOWAK ,SEWERYN " action="MISS" type="JUMPER" paint="Y" x="6.5500001907348633" y="66.0999984741211" side="left">
      </play>
      <play vh="V" time="06:49" uni="11" team="ZAC" checkname="CHAC,FRANCISZEK" action="REBOUND" type="DEF" side="right">
      </play>
      <play vh="H" time="06:29" uni="7" team="ŚLĄ" checkname="CHLEBIEJ ,FILIP" action="FOUL" side="left">
      </play>
      <play vh="V" time="06:29" uni="8" team="ZAC" checkname="DĘBICKI,MACIEJ" action="SUB" type="OUT" side="right">
      </play>
      <play vh="V" time="06:29" uni="16" team="ZAC" checkname="WOŹNIAK,FILIP" action="SUB" type="IN" side="right">
      </play>
      <play vh="V" time="06:29" uni="15" team="ZAC" checkname="JAROSZ,MACIEJ" action="GOOD" type="FT" vscore="5" hscore="3" side="right">
      </play>
      <play vh="V" time="06:29" uni="7" team="ZAC" checkname="BERLIŃSKI,VINCENT" action="ASSIST" side="right">
      </play>
      <play vh="V" time="06:29" uni="15" team="ZAC" checkname="JAROSZ,MACIEJ" action="MISS" type="FT" side="right">
      </play>
      <play vh="H" time="06:29" uni="TM" team="ŚLĄ" checkname="TEAM" action="REBOUND" type="DEF" side="left">
      </play>
      <play vh="H" time="06:29" uni="4" team="ŚLĄ" checkname="MACIEJEWSKI,PAWEŁ" action="SUB" type="OUT" side="left">
      </play>
      <play vh="H" time="06:29" uni="10" team="ŚLĄ" checkname="PRATSZ,JAN" action="SUB" type="IN" side="left">
      </play>
      <play vh="H" time="06:24" uni="10" team="ŚLĄ" checkname="PRATSZ,JAN" action="TURNOVER" side="left">
      </play>
      <play vh="V" time="06:24" uni="7" team="ZAC" checkname="BERLIŃSKI,VINCENT" action="STEAL" side="right">
      </play>
      <play vh="H" time="06:21" uni="10" team="ŚLĄ" checkname="PRATSZ,JAN" action="FOUL" side="left">
      </play>
      <play vh="V" time="06:20" uni="15" team="ZAC" checkname="JAROSZ,MACIEJ" action="MISS" type="JUMPER" paint="Y" x="86.120002746582031" y="50.279998779296875" side="right">
      </play>
      <play vh="H" time="06:20" uni="7" team="ŚLĄ" checkname="CHLEBIEJ ,FILIP" action="BLOCK" side="left">
      </play>
      <play vh="V" time="06:16" uni="16" team="ZAC" checkname="WOŹNIAK,FILIP" action="REBOUND" type="OFF" side="right">
      </play>
      <play vh="V" time="06:15" uni="16" team="ZAC" checkname="WOŹNIAK,FILIP" action="TURNOVER" side="right">
      </play>
    </period>
  </plays>
</bbgame>